{
  "schema_version": "1.0",
  "run_id": "security-overhead-final-factorial-mtls-b5-rf3-isr3-msg102400-tps10000-batch131072-acksall-prod1-compnone-trial1",
  "security_mode": "mtls",
  "baseline_name": "security-overhead-final-factorial",
  "sweep_name": "security-overhead-final-factorial",
  "sweep_variable": "factorial_config",
  "sweep_value": "security-overhead-final-factorial-mtls-b5-rf3-isr3-msg102400-tps10000-batch131072-acksall-prod1-compnone-trial1",
  "trial_index": 1,
  "trial_count": 3,
  "topic": "benchmark-topic-security-overhead-final-factorial-mtls-b5-rf3-isr3-msg102400-tps10000-batch131072-acksall-prod1-compnone-trial1",
  "cluster": {
    "bootstrap_servers": "10.20.1.69:9094,10.20.1.238:9094,10.20.1.91:9094,10.20.1.118:9094,10.20.1.53:9094",
    "broker_count": 5,
    "partitions": 6,
    "replication_factor": 3,
    "min_insync_replicas": 3
  },
  "run_config": {
    "num_records": 100000,
    "record_size_bytes": 102400,
    "throughput_limit_records_per_sec": 10000,
    "producer_count": 1,
    "consumer_count": 1,
    "batch_size": 131072,
    "linger_ms": 5,
    "acks": "all",
    "compression_type": "none"
  },
  "metrics": {
    "records_sent": 100000,
    "throughput_records_per_sec": 1574.679159,
    "throughput_mb_per_sec": 153.78,
    "avg_latency_ms": 43.2,
    "max_latency_ms": 1394.0,
    "producer_count_observed": 1,
    "producer_throughput_records_per_sec_min": 1574.679159,
    "producer_throughput_records_per_sec_max": 1574.679159,
    "producer_avg_latency_ms_min": 43.2,
    "producer_avg_latency_ms_max": 43.2,
    "interval_summary_count": 12,
    "interval_avg_latency_ms_p95": 198.63499999999988,
    "interval_avg_latency_ms_p99": 256.84700000000004,
    "interval_max_latency_ms_p95": 837.9499999999994,
    "interval_max_latency_ms_p99": 1282.7900000000004,
    "producer_summaries": [
      {
        "summary_line": "100000 records sent, 1574.679159 records/sec (153.78 MB/sec), 43.20 ms avg latency, 1394.00 ms max latency, 19 ms 50th, 152 ms 95th, 363 ms 99th, 910 ms 99.9th.",
        "records_sent": 100000,
        "throughput_records_per_sec": 1574.679159,
        "throughput_mb_per_sec": 153.78,
        "avg_latency_ms": 43.2,
        "max_latency_ms": 1394.0
      }
    ],
    "interval_summaries": [
      {
        "summary_line": "2488 records sent, 497.6 records/sec (48.59 MB/sec), 271.4 ms avg latency, 1394.0 ms max latency.",
        "records_sent": 2488,
        "throughput_records_per_sec": 497.6,
        "throughput_mb_per_sec": 48.59,
        "avg_latency_ms": 271.4,
        "max_latency_ms": 1394.0,
        "producer_index": 1,
        "producer_count": 1
      },
      {
        "summary_line": "5604 records sent, 1120.8 records/sec (109.45 MB/sec), 10.6 ms avg latency, 51.0 ms max latency.",
        "records_sent": 5604,
        "throughput_records_per_sec": 1120.8,
        "throughput_mb_per_sec": 109.45,
        "avg_latency_ms": 10.6,
        "max_latency_ms": 51.0,
        "producer_index": 1,
        "producer_count": 1
      },
      {
        "summary_line": "6398 records sent, 1279.3 records/sec (124.94 MB/sec), 10.3 ms avg latency, 48.0 ms max latency.",
        "records_sent": 6398,
        "throughput_records_per_sec": 1279.3,
        "throughput_mb_per_sec": 124.94,
        "avg_latency_ms": 10.3,
        "max_latency_ms": 48.0,
        "producer_index": 1,
        "producer_count": 1
      },
      {
        "summary_line": "8370 records sent, 1674.0 records/sec (163.48 MB/sec), 20.8 ms avg latency, 99.0 ms max latency.",
        "records_sent": 8370,
        "throughput_records_per_sec": 1674.0,
        "throughput_mb_per_sec": 163.48,
        "avg_latency_ms": 20.8,
        "max_latency_ms": 99.0,
        "producer_index": 1,
        "producer_count": 1
      },
      {
        "summary_line": "8532 records sent, 1706.4 records/sec (166.64 MB/sec), 17.6 ms avg latency, 81.0 ms max latency.",
        "records_sent": 8532,
        "throughput_records_per_sec": 1706.4,
        "throughput_mb_per_sec": 166.64,
        "avg_latency_ms": 17.6,
        "max_latency_ms": 81.0,
        "producer_index": 1,
        "producer_count": 1
      },
      {
        "summary_line": "9130 records sent, 1826.0 records/sec (178.32 MB/sec), 19.8 ms avg latency, 84.0 ms max latency.",
        "records_sent": 9130,
        "throughput_records_per_sec": 1826.0,
        "throughput_mb_per_sec": 178.32,
        "avg_latency_ms": 19.8,
        "max_latency_ms": 84.0,
        "producer_index": 1,
        "producer_count": 1
      },
      {
        "summary_line": "9035 records sent, 1807.0 records/sec (176.46 MB/sec), 61.9 ms avg latency, 221.0 ms max latency.",
        "records_sent": 9035,
        "throughput_records_per_sec": 1807.0,
        "throughput_mb_per_sec": 176.46,
        "avg_latency_ms": 61.9,
        "max_latency_ms": 221.0,
        "producer_index": 1,
        "producer_count": 1
      },
      {
        "summary_line": "8563 records sent, 1712.3 records/sec (167.21 MB/sec), 69.6 ms avg latency, 346.0 ms max latency.",
        "records_sent": 8563,
        "throughput_records_per_sec": 1712.3,
        "throughput_mb_per_sec": 167.21,
        "avg_latency_ms": 69.6,
        "max_latency_ms": 346.0,
        "producer_index": 1,
        "producer_count": 1
      },
      {
        "summary_line": "8285 records sent, 1656.7 records/sec (161.78 MB/sec), 139.1 ms avg latency, 383.0 ms max latency.",
        "records_sent": 8285,
        "throughput_records_per_sec": 1656.7,
        "throughput_mb_per_sec": 161.78,
        "avg_latency_ms": 139.1,
        "max_latency_ms": 383.0,
        "producer_index": 1,
        "producer_count": 1
      },
      {
        "summary_line": "9155 records sent, 1831.0 records/sec (178.81 MB/sec), 24.5 ms avg latency, 137.0 ms max latency.",
        "records_sent": 9155,
        "throughput_records_per_sec": 1831.0,
        "throughput_mb_per_sec": 178.81,
        "avg_latency_ms": 24.5,
        "max_latency_ms": 137.0,
        "producer_index": 1,
        "producer_count": 1
      },
      {
        "summary_line": "9089 records sent, 1817.8 records/sec (177.52 MB/sec), 19.6 ms avg latency, 75.0 ms max latency.",
        "records_sent": 9089,
        "throughput_records_per_sec": 1817.8,
        "throughput_mb_per_sec": 177.52,
        "avg_latency_ms": 19.6,
        "max_latency_ms": 75.0,
        "producer_index": 1,
        "producer_count": 1
      },
      {
        "summary_line": "9056 records sent, 1811.2 records/sec (176.88 MB/sec), 17.6 ms avg latency, 68.0 ms max latency.",
        "records_sent": 9056,
        "throughput_records_per_sec": 1811.2,
        "throughput_mb_per_sec": 176.88,
        "avg_latency_ms": 17.6,
        "max_latency_ms": 68.0,
        "producer_index": 1,
        "producer_count": 1
      }
    ]
  },
  "host_telemetry": {
    "enabled": true,
    "sample_interval_seconds": null,
    "host_count": 6,
    "hosts": [
      {
        "role": "benchmark_client",
        "host_id": "benchmark-client",
        "sample_count": 74,
        "started_at": "2026-04-20T02:38:53Z",
        "ended_at": "2026-04-20T02:40:08Z",
        "cpu_percent_mean": 75.97486486486487,
        "cpu_percent_max": 100.0,
        "memory_used_percent_mean": 9.582432432432432,
        "memory_used_percent_max": 10.86,
        "network_rx_bytes_delta": 35368593,
        "network_tx_bytes_delta": 10390494486,
        "disk_read_sectors_delta": 0,
        "disk_write_sectors_delta": 53288,
        "source_file": "benchmark-client.jsonl"
      },
      {
        "role": "broker",
        "host_id": "broker-1",
        "sample_count": 76,
        "started_at": "2026-04-20T02:38:54Z",
        "ended_at": "2026-04-20T02:40:12Z",
        "cpu_percent_mean": 44.28197368421053,
        "cpu_percent_max": 79.0,
        "memory_used_percent_mean": 24.033421052631578,
        "memory_used_percent_max": 25.67,
        "network_rx_bytes_delta": 5891329124,
        "network_tx_bytes_delta": 3957933702,
        "disk_read_sectors_delta": 20600,
        "disk_write_sectors_delta": 11213720,
        "source_file": "broker-1.jsonl"
      },
      {
        "role": "broker",
        "host_id": "broker-2",
        "sample_count": 78,
        "started_at": "2026-04-20T02:38:55Z",
        "ended_at": "2026-04-20T02:40:15Z",
        "cpu_percent_mean": 45.011923076923075,
        "cpu_percent_max": 74.5,
        "memory_used_percent_mean": 23.330000000000002,
        "memory_used_percent_max": 25.23,
        "network_rx_bytes_delta": 7274508481,
        "network_tx_bytes_delta": 3736111470,
        "disk_read_sectors_delta": 20096,
        "disk_write_sectors_delta": 13574752,
        "source_file": "broker-2.jsonl"
      },
      {
        "role": "broker",
        "host_id": "broker-3",
        "sample_count": 81,
        "started_at": "2026-04-20T02:38:56Z",
        "ended_at": "2026-04-20T02:40:19Z",
        "cpu_percent_mean": 44.02654320987654,
        "cpu_percent_max": 74.37,
        "memory_used_percent_mean": 23.732469135802468,
        "memory_used_percent_max": 25.53,
        "network_rx_bytes_delta": 6482762360,
        "network_tx_bytes_delta": 5349809349,
        "disk_read_sectors_delta": 19888,
        "disk_write_sectors_delta": 12620720,
        "source_file": "broker-3.jsonl"
      },
      {
        "role": "broker",
        "host_id": "broker-4",
        "sample_count": 83,
        "started_at": "2026-04-20T02:38:56Z",
        "ended_at": "2026-04-20T02:40:22Z",
        "cpu_percent_mean": 44.433614457831325,
        "cpu_percent_max": 82.61,
        "memory_used_percent_mean": 23.015301204819277,
        "memory_used_percent_max": 23.43,
        "network_rx_bytes_delta": 6316244912,
        "network_tx_bytes_delta": 3632464407,
        "disk_read_sectors_delta": 20624,
        "disk_write_sectors_delta": 11973296,
        "source_file": "broker-4.jsonl"
      },
      {
        "role": "broker",
        "host_id": "broker-5",
        "sample_count": 86,
        "started_at": "2026-04-20T02:38:57Z",
        "ended_at": "2026-04-20T02:40:25Z",
        "cpu_percent_mean": 32.70476744186047,
        "cpu_percent_max": 72.14,
        "memory_used_percent_mean": 23.71104651162791,
        "memory_used_percent_max": 25.36,
        "network_rx_bytes_delta": 5252720486,
        "network_tx_bytes_delta": 4265707560,
        "disk_read_sectors_delta": 10304,
        "disk_write_sectors_delta": 9110224,
        "source_file": "broker-5.jsonl"
      }
    ],
    "broker_cpu_percent_mean": 42.09176437414039,
    "broker_cpu_percent_max_mean": 76.524,
    "benchmark_client_cpu_percent_mean": 75.97486486486487,
    "broker_memory_used_percent_mean": 23.564447580976246,
    "benchmark_client_memory_used_percent_mean": 9.582432432432432,
    "broker_network_rx_bytes_delta_mean": 6243513072.6,
    "broker_network_tx_bytes_delta_mean": 4188405297.6,
    "broker_network_rx_bytes_delta_total": 31217565363,
    "broker_network_tx_bytes_delta_total": 20942026488,
    "benchmark_client_network_rx_bytes_delta": 35368593,
    "benchmark_client_network_tx_bytes_delta": 10390494486,
    "broker_disk_read_sectors_delta_mean": 18302.4,
    "broker_disk_write_sectors_delta_mean": 11698542.4,
    "broker_disk_read_sectors_delta_total": 91512,
    "broker_disk_write_sectors_delta_total": 58492712,
    "benchmark_client_disk_read_sectors_delta": 0,
    "benchmark_client_disk_write_sectors_delta": 53288,
    "source_directory": "host-telemetry"
  },
  "files": {
    "raw_output": "/var/lib/kafka-client/results/security-overhead-final-factorial-mtls-b5-rf3-isr3-msg102400-tps10000-batch131072-acksall-prod1-compnone-trial1/producer-perf.log",
    "metadata": "metadata.json"
  },
  "raw_summary_lines": [
    "100000 records sent, 1574.679159 records/sec (153.78 MB/sec), 43.20 ms avg latency, 1394.00 ms max latency, 19 ms 50th, 152 ms 95th, 363 ms 99th, 910 ms 99.9th."
  ]
}
